moveread/core/__init__.py
moveread/core/__init__.pyi
moveread/core/_types.py
moveread/core/core.py
moveread/core/export.py
moveread/core/labels.py
moveread/core/cli/__init__.py
moveread/core/cli/__init__.pyi
moveread/core/cli/export.py
moveread/core/cli/list.py
moveread/core/cli/main.py
moveread/core/cli/util.py
moveread_core-0.4.3.dist-info/METADATA
moveread_core-0.4.3.dist-info/WHEEL
moveread_core-0.4.3.dist-info/entry_points.txt
moveread_core-0.4.3.dist-info/top_level.txt
moveread_core-0.4.3.dist-info/RECORD
