Metadata-Version: 2.1
Name: moveread-core
Version: 0.4.3
Summary: Core Moveread Dataset
Author-email: Marcel Claramunt <marcel@moveread.com>
Project-URL: repo, https://github.com/moveread/core.git
Requires-Python: >=3.10
Requires-Dist: pydantic
Requires-Dist: haskellian
Requires-Dist: robust-extraction2
Requires-Dist: pure-cv
Requires-Dist: chess-pairings
Requires-Dist: chess-notation
Requires-Dist: python-kv
Requires-Dist: scoresheet-models
Requires-Dist: chess-utils
Requires-Dist: sequence-edits
Provides-Extra: cli
Requires-Dist: ocr-dataset; extra == "cli"
Requires-Dist: files-dataset; extra == "cli"
Requires-Dist: typer; extra == "cli"
Requires-Dist: fs-tools; extra == "cli"
Requires-Dist: python-dotenv; extra == "cli"
Requires-Dist: typer-tools; extra == "cli"
